[
   {
      "sehri":"2023-03-13 04:39:00",
      "iftar":"2023-03-13 14:14:00"
   },
   {
      "sehri":"2023-03-14 04:38:00",
      "iftar":"2023-03-14 18:14:00"
   },
   {
      "sehri":"2023-03-25 04:37:00",
      "iftar":"2023-03-25 18:15:00"
   },
   {
      "sehri":"2023-03-26 04:36:00",
      "iftar":"2023-03-26 18:15:00"
   },
   {
      "sehri":"2023-03-27 04:35:00",
      "iftar":"2023-03-27 18:16:00"
   },
   {
      "sehri":"2023-03-28 04:34:00",
      "iftar":"2023-03-28 18:16:00"
   },
   {
      "sehri":"2023-03-29 04:32:00",
      "iftar":"2023-03-29 18:17:00"
   },
   {
      "sehri":"2023-03-30 04:31:00",
      "iftar":"2023-03-30 18:17:00"
   },
   {
      "sehri":"2023-03-31 04:30:00",
      "iftar":"2023-03-31 18:18:00"
   },
   {
      "sehri":"2023-04-01 04:29:00",
      "iftar":"2023-04-01 18:18:00"
   },
   {
      "sehri":"2023-04-02 04:28:00",
      "iftar":"2023-04-02 18:19:00"
   },
   {
      "sehri":"2023-04-03 04:27:00",
      "iftar":"2023-04-03 18:19:00"
   },
   {
      "sehri":"2023-04-04 04:26:00",
      "iftar":"2023-04-04 18:19:00"
   },
   {
      "sehri":"2023-04-05 04:25:00",
      "iftar":"2023-04-05 18:20:00"
   },
   {
      "sehri":"2023-04-06 04:24:00",
      "iftar":"2023-04-06 18:20:00"
   },
   {
      "sehri":"2023-04-07 04:23:00",
      "iftar":"2023-04-07 18:21:00"
   },
   {
      "sehri":"2023-04-08 04:22:00",
      "iftar":"2023-04-08 18:21:00"
   },
   {
      "sehri":"2023-04-09 04:21:00",
      "iftar":"2023-04-09 18:21:00"
   },
   {
      "sehri":"2023-04-10 04:20:00",
      "iftar":"2023-04-10 18:22:00"
   },
   {
      "sehri":"2023-04-11 04:19:00",
      "iftar":"2023-04-11 18:22:00"
   },
   {
      "sehri":"2023-04-12 04:18:00",
      "iftar":"2023-04-12 18:23:00"
   },
   {
      "sehri":"2023-04-13 04:17:00",
      "iftar":"2023-04-13 18:23:00"
   },
   {
      "sehri":"2023-04-14 04:15:00",
      "iftar":"2023-04-14 18:23:00"
   },
   {
      "sehri":"2023-04-15 04:14:00",
      "iftar":"2023-04-15 18:24:00"
   },
   {
      "sehri":"2023-04-16 04:13:00",
      "iftar":"2023-04-16 18:24:00"
   },
   {
      "sehri":"2023-04-17 04:12:00",
      "iftar":"2023-04-17 18:24:00"
   },
   {
      "sehri":"2023-04-18 04:11:00",
      "iftar":"2023-04-18 18:25:00"
   },
   {
      "sehri":"2023-04-19 04:10:00",
      "iftar":"2023-04-19 18:25:00"
   },
   {
      "sehri":"2023-04-20 04:09:00",
      "iftar":"2023-04-20 18:26:00"
   },
   {
      "sehri":"2023-04-21 04:08:00",
      "iftar":"2023-04-21 18:26:00"
   },
   {
      "sehri":"2023-04-22 04:07:00",
      "iftar":"2023-04-22 18:27:00"
   }
]
